<annotation><filename>20191028a-gardenandhappy.com_.jpg</filename><size><width>1920</width><height>1440</height><depth>3</depth></size><object><name>unripe</name><bndbox><xmin>1065</xmin><ymin>887</ymin><xmax>1206</xmax><ymax>1002</ymax></bndbox></object><object><name>unripe</name><bndbox><xmin>1470</xmin><ymin>1099</ymin><xmax>1647</xmax><ymax>1287</ymax></bndbox></object><object><name>ripe</name><bndbox><xmin>707</xmin><ymin>66</ymin><xmax>1053</xmax><ymax>324</ymax></bndbox></object><object><name>ripe</name><bndbox><xmin>905</xmin><ymin>329</ymin><xmax>1283</xmax><ymax>604</ymax></bndbox></object><object><name>ripe</name><bndbox><xmin>1281</xmin><ymin>1022</ymin><xmax>1528</xmax><ymax>1182</ymax></bndbox></object><object><name>unripe</name><bndbox><xmin>1265</xmin><ymin>878</ymin><xmax>1546</xmax><ymax>1107</ymax></bndbox></object><object><name>unripe</name><bndbox><xmin>1125</xmin><ymin>610</ymin><xmax>1402</xmax><ymax>925</ymax></bndbox></object><object><name>unripe</name><bndbox><xmin>981</xmin><ymin>615</ymin><xmax>1218</xmax><ymax>878</ymax></bndbox></object><object><name>ripe</name><bndbox><xmin>624</xmin><ymin>502</ymin><xmax>1015</xmax><ymax>880</ymax></bndbox></object><object><name>unripe</name><bndbox><xmin>491</xmin><ymin>158</ymin><xmax>768</xmax><ymax>412</ymax></bndbox></object><object><name>ripe</name><bndbox><xmin>342</xmin><ymin>333</ymin><xmax>671</xmax><ymax>651</ymax></bndbox></object><object><name>unripe</name><bndbox><xmin>417</xmin><ymin>586</ymin><xmax>642</xmax><ymax>804</ymax></bndbox></object><object><name>unripe</name><bndbox><xmin>340</xmin><ymin>622</ymin><xmax>529</xmax><ymax>840</ymax></bndbox></object><object><name>unripe</name><bndbox><xmin>64</xmin><ymin>469</ymin><xmax>275</xmax><ymax>630</ymax></bndbox></object><object><name>unripe</name><bndbox><xmin>3</xmin><ymin>964</ymin><xmax>93</xmax><ymax>1089</ymax></bndbox></object><object><name>unripe</name><bndbox><xmin>194</xmin><ymin>1067</ymin><xmax>306</xmax><ymax>1177</ymax></bndbox></object><object><name>unripe</name><bndbox><xmin>329</xmin><ymin>963</ymin><xmax>541</xmax><ymax>1148</ymax></bndbox></object></annotation>